pytest_sugar.py
pytest_sugar-1.1.1.dist-info/LICENSE
pytest_sugar-1.1.1.dist-info/METADATA
pytest_sugar-1.1.1.dist-info/WHEEL
pytest_sugar-1.1.1.dist-info/entry_points.txt
pytest_sugar-1.1.1.dist-info/top_level.txt
pytest_sugar-1.1.1.dist-info/RECORD
