Metadata-Version: 2.1
Name: pytest-sugar
Version: 1.1.1
Summary: pytest-sugar is a plugin for pytest that changes the default look and feel of pytest (e.g. progressbar, show tests that fail instantly).
Home-page: https://github.com/Teemu/pytest-sugar
Author: Teemu, Janne Vanhala and others
Author-email: orkkiolento@gmail.com, janne.vanhala@gmail.com
License: BSD
Project-URL: Issue Tracker, https://github.com/Teemu/pytest-sugar/issues
Platform: any
Classifier: Development Status :: 4 - Beta
Classifier: Intended Audience :: Developers
Classifier: License :: OSI Approved :: BSD License
Classifier: Operating System :: POSIX
Classifier: Operating System :: Microsoft :: Windows
Classifier: Operating System :: MacOS :: MacOS X
Classifier: Topic :: Software Development :: Testing
Classifier: Topic :: Software Development :: Libraries
Classifier: Topic :: Utilities
Classifier: Programming Language :: Python :: 3
Classifier: Programming Language :: Python :: 3.8
Classifier: Programming Language :: Python :: 3.9
Classifier: Programming Language :: Python :: 3.10
Classifier: Programming Language :: Python :: 3.11
Classifier: Programming Language :: Python :: 3.12
Classifier: Programming Language :: Python :: 3.13
Classifier: Programming Language :: Python :: Implementation :: PyPy
Provides-Extra: dev
License-File: LICENSE
